<?xml version="1.0" encoding="UTF-8"?>

<Player ObjectClass="Immortal">
  <Name>Shinigami</Name>
  <PName></PName>
  <ShortDesc></ShortDesc>
  <PShortDesc></PShortDesc>
  <Description></Description>
  <Sex>male</Sex>
  <Level>104</Level>
  <Race>1</Race>
  <Class>11</Class>
  <Alignment>0</Alignment>
  <Size>0</Size>
  <Position>9</Position>
  <WimpyFlee>-2147483648</WimpyFlee>
  <WimpyBlink>-2147483648</WimpyBlink>
  <WimpyRecall>-2147483648</WimpyRecall>
  <WimpyPray>-2147483648</WimpyPray>
  <ResCold>0</ResCold>
  <ResFire>0</ResFire>
  <ResAcid>0</ResAcid>
  <ResElec>0</ResElec>
  <ResPois>0</ResPois>
  <ResMind>0</ResMind>
  <ResSleep>0</ResSleep>
  <ResCharm>0</ResCharm>
  <Strength>14</Strength>
  <Dexterity>8</Dexterity>
  <Intelligence>15</Intelligence>
  <Wisdom>7</Wisdom>
  <Constitution>5</Constitution>
  <HitPoints>1789</HitPoints>
  <HitPointsMax>1789</HitPointsMax>
  <Energy>3588</Energy>
  <EnergyMax>3588</EnergyMax>
  <Moves>2028</Moves>
  <MovesMax>2028</MovesMax>
  <ExpTNL>142058920</ExpTNL>
  <LevelLast>0</LevelLast>
  <LevelHitT>4</LevelHitT>
  <LevelEnergyT>3</LevelEnergyT>
  <LevelMoveT>5</LevelMoveT>
  <InRoom>1179648</InRoom>
  <Carrying ObjectClass="ObjectHolder">
    <Object ObjectClass="Object" VRef="393220">
      <WearLoc>-1</WearLoc>
    </Object>
    <Object ObjectClass="Object" VRef="1572870">
      <WearLoc>-1</WearLoc>
    </Object>
    <Object ObjectClass="Object" VRef="1900630">
      <WearLoc>-1</WearLoc>
    </Object>
    <Object ObjectClass="Object" VRef="1179665">
      <WearLoc>-1</WearLoc>
    </Object>
    <Object ObjectClass="Object" VRef="1179666">
      <WearLoc>-1</WearLoc>
    </Object>
    <Object ObjectClass="Object" VRef="1179668">
      <WearLoc>-1</WearLoc>
    </Object>
  </Carrying>
  <Wearing ObjectClass="ObjectHolder">
    <Object ObjectClass="Object" VRef="1310720">
      <WearLoc>34</WearLoc>
    </Object>
    <Object ObjectClass="Object" VRef="131089">
      <WearLoc>28</WearLoc>
    </Object>
    <Object ObjectClass="Object" VRef="917506">
      <WearLoc>8</WearLoc>
    </Object>
    <Object ObjectClass="Object" VRef="851974">
      <WearLoc>9</WearLoc>
    </Object>
    <Object ObjectClass="Object" VRef="1376265">
      <WearLoc>29</WearLoc>
      <Contents ObjectClass="ObjectHolder">
        <Object ObjectClass="Object" VRef="524303">
          <WearLoc>-1</WearLoc>
        </Object>
        <Object ObjectClass="Object" VRef="524303">
          <WearLoc>-1</WearLoc>
        </Object>
        <Object ObjectClass="Object" VRef="524303">
          <WearLoc>-1</WearLoc>
        </Object>
        <Object ObjectClass="Object" VRef="524303">
          <WearLoc>-1</WearLoc>
        </Object>
        <Object ObjectClass="Object" VRef="524303">
          <WearLoc>-1</WearLoc>
        </Object>
        <Object ObjectClass="Object" VRef="524303">
          <WearLoc>-1</WearLoc>
        </Object>
        <Object ObjectClass="Object" VRef="524303">
          <WearLoc>-1</WearLoc>
        </Object>
        <Object ObjectClass="Object" VRef="524303">
          <WearLoc>-1</WearLoc>
        </Object>
        <Object ObjectClass="Object" VRef="524303">
          <WearLoc>-1</WearLoc>
        </Object>
        <Object ObjectClass="Object" VRef="524303">
          <WearLoc>-1</WearLoc>
        </Object>
      </Contents>
    </Object>
    <Object ObjectClass="Object" VRef="327702">
      <WearLoc>26</WearLoc>
    </Object>
    <Object ObjectClass="Object" VRef="131088">
      <WearLoc>1</WearLoc>
    </Object>
    <Object ObjectClass="Object" VRef="917509">
      <WearLoc>11</WearLoc>
    </Object>
    <Object ObjectClass="Object" VRef="917511">
      <WearLoc>13</WearLoc>
    </Object>
    <Object ObjectClass="Object" VRef="917510">
      <WearLoc>6</WearLoc>
    </Object>
    <Object ObjectClass="Object" VRef="917504">
      <WearLoc>24</WearLoc>
    </Object>
  </Wearing>
  <UID>12</UID>
  <Passwd>b3JhbmdlbXVk</Passwd>
  <Prompt>[^r%hhp^x ^g%ee^x ^b%mmv^x] ^w%x^x&gt;&gt;</Prompt>
  <Title></Title>
  <TitleAFK></TitleAFK>
  <Email></Email>
  <Homepage></Homepage>
  <LastLogin>978712259</LastLogin>
  <TimePlayed>761277</TimePlayed>
  <Trust>104</Trust>
  <Scroll>20</Scroll>
  <InvisLevel>0</InvisLevel>
  <FlagsOptions>537002607</FlagsOptions>
  <FlagsInfo>1358960595</FlagsInfo>
  <CondDrunk>0</CondDrunk>
  <CondFull>35</CondFull>
  <CondThirst>-1</CondThirst>
  <CondHunger>-1</CondHunger>
  <CondHigh>0</CondHigh>
  <CondWithdrawl>0</CondWithdrawl>
  <ColorPref Index="0">516</ColorPref>
  <ColorPref Index="1">128</ColorPref>
  <ColorPref Index="2">1</ColorPref>
  <ColorPref Index="3">1</ColorPref>
  <ColorPref Index="4">2048</ColorPref>
  <ColorPref Index="5">256</ColorPref>
  <ColorPref Index="6">130</ColorPref>
  <ColorPref Index="7">130</ColorPref>
  <ColorPref Index="8">6</ColorPref>
  <ColorPref Index="9">2048</ColorPref>
  <ColorPref Index="10">262</ColorPref>
  <ColorPref Index="11">520</ColorPref>
  <ColorPref Index="12">514</ColorPref>
  <ColorPref Index="13">1024</ColorPref>
  <ColorPref Index="14">4096</ColorPref>
  <ColorPref Index="15">72</ColorPref>
  <ColorPref Index="16">66</ColorPref>
  <ColorPref Index="17">131072</ColorPref>
  <ColorPref Index="18">512</ColorPref>
  <ColorPref Index="19">128</ColorPref>
  <ColorPref Index="20">2050</ColorPref>
  <ColorPref Index="21">128</ColorPref>
  <ColorPref Index="22">1</ColorPref>
  <ColorPref Index="23">1</ColorPref>
  <ColorPref Index="24">2052</ColorPref>
  <ColorPref Index="25">2</ColorPref>
  <ColorPref Index="26">128</ColorPref>
  <InvisLevel>0</InvisLevel>
  <PoofIn></PoofIn>
  <PoofOut></PoofOut>
  <GoInvisSelf></GoInvisSelf>
  <GoInvisRoom></GoInvisRoom>
  <GoVisSelf></GoVisSelf>
  <GoVisRoom></GoVisRoom>
  <MakeObjOneSelf></MakeObjOneSelf>
  <MakeObjOneRoom></MakeObjOneRoom>
  <MakeObjMultiSelf></MakeObjMultiSelf>
  <MakeObjMultiRoom></MakeObjMultiRoom>
  <MakeMobOneSelf></MakeMobOneSelf>
  <MakeMobOneRoom></MakeMobOneRoom>
  <MakeMobMultiSelf></MakeMobMultiSelf>
  <MakeMobMultiRoom></MakeMobMultiRoom>
</Player>
